rpcplugin/__init__.py
rpcplugin-0.0.1.dist-info/LICENSE
rpcplugin-0.0.1.dist-info/METADATA
rpcplugin-0.0.1.dist-info/WHEEL
rpcplugin-0.0.1.dist-info/top_level.txt
rpcplugin-0.0.1.dist-info/RECORD
