Metadata-Version: 2.1
Name: rpcplugin
Version: 0.0.1
Summary: gRPC-based plugin system
Home-page: https://github.com/rpcplugin/python
Author: Martin Atkins
Author-email: mart@degeneration.co.uk
License: UNKNOWN
Platform: UNKNOWN
Classifier: Programming Language :: Python :: 3
Classifier: License :: OSI Approved :: MIT License
Classifier: Operating System :: OS Independent
